Workbook

Sheet Summary
A1: Sweetgreen Lab 1 sandbox | B1: Value | C1: Definition
A2: Scenario | B2: Synthetic | C2: 30 digital orders; one modeled store; 18 September 2026
A3: Orders | B3: =COUNTA(Orders!A2:A31) -> 30 | C3: All orders in the sample
A4: Reworked orders | B4: =COUNTIF(KitchenRuns!E2:E31,"Rework") -> 6 | C4: D2 rejected; re-entered as Rework; later completed
A5: Rework rate | B5: =B4/B3 -> 0.2 | C5: Reworked orders / all orders
A6: Availability mismatches | B6: =SUM(MenuItems!H2:H25) -> 10 | C6: Current versus independent nightly source; 24 configurations
A7: Affected late minutes | B7: =SUM(Calculations!E2:E31) -> 112 | C7: Sum of readiness lateness, floored at zero
A8: Mean affected lateness | B8: =B7/B4 -> 18.666667 | C8: Minutes past promise, six reworked orders
A9: Extra labor minutes | B9: =SUM(Calculations!F2:F31) -> 60 | C9: Manual recovery effort on affected orders
A10: Labor capacity value | B10: =SUM(Calculations!G2:G31) -> 24 | C10: Extra labor minutes × $0.40/minute assumption
A11: Discarded partial prep | B11: =SUM(Calculations!H2:H31) -> 28 | C11: Recorded synthetic food waste
A12: Goodwill refunds | B12: =SUM(Calculations!I2:I31) -> 20 | C12: Captured-order refunds; separate from costs
A13: Total modeled burden | B13: =SUM(B10:B12) -> 72 | C13: Food + labor value + refunds; not a company-wide estimate
A14: Burden per reworked order | B14: =B13/B4 -> 12 | C14: Modeled burden / six reworked orders
A15: Captured gross receipts | B15: =SUM(Payments!D2:D31) -> 644 | C15: Captured amount before refunds; excludes tax/tips
A16: Net receipts | B16: =SUM(Payments!F2:F31) -> 624 | C16: Captured gross receipts minus refunds
A17: Trace order | B17: O001 | C17: Menu M001 → line L001 → run K001 → exception E001 → payment P001
A18: Lab 2 target | B18: D2 | C18: Requested configuration available? Demonstrate stale-source failure, then freshness gate.
A19: Lab 3 target | B19: D3 | C19: Recovery choice: urgency, prep ETA, queue impact and constraints/consent.
A20: Boundary | B20: Hypothesis | C20: Source mismatch is injected. Actual Sweetgreen prevalence and causal effect remain unverified.

Sheet Customers
A1: CustomerID | B1: Name | C1: Segment
A2: C001 | B2: Synthetic Guest 01 | C2: Pickup
A3: C002 | B3: Synthetic Guest 02 | C3: Delivery
A4: C003 | B4: Synthetic Guest 03 | C4: Pickup
A5: C004 | B5: Synthetic Guest 04 | C5: Delivery
A6: C005 | B6: Synthetic Guest 05 | C6: Pickup
A7: C006 | B7: Synthetic Guest 06 | C7: Delivery
A8: C007 | B8: Synthetic Guest 07 | C8: Pickup
A9: C008 | B9: Synthetic Guest 08 | C9: Delivery
A10: C009 | B10: Synthetic Guest 09 | C10: Pickup
A11: C010 | B11: Synthetic Guest 10 | C11: Delivery
A12: C011 | B12: Synthetic Guest 11 | C12: Pickup
... A25: C024 | B25: Synthetic Guest 24 | C25: Delivery

Sheet MenuItems
A1: SKU | B1: Description | C1: CurrentAvailable | D1: VerifiedAt | E1: UnitPrice | F1: EvidenceType | G1: CachedAvailable (lookup) | H1: Mismatch (derived)
A2: M001 | B2: Synthetic meal configuration 01 | C2: 0 | D2: 46283.49 | E2: 15 | F2: Synthetic scenario | G2: =INDEX(LegacyAvailability!$B$2:$B$25,MATCH(A2,LegacyAvailability!$A$2:$A$25,0)) -> 1 | H2: =IF(C2=G2,0,1) -> 1
A3: M002 | B3: Synthetic meal configuration 02 | C3: 0 | D3: 46283.49 | E3: 16 | F3: Synthetic scenario | G3: =INDEX(LegacyAvailability!$B$2:$B$25,MATCH(A3,LegacyAvailability!$A$2:$A$25,0)) -> 1 | H3: =IF(C3=G3,0,1) -> 1
A4: M003 | B4: Synthetic meal configuration 03 | C4: 0 | D4: 46283.49 | E4: 17 | F4: Synthetic scenario | G4: =INDEX(LegacyAvailability!$B$2:$B$25,MATCH(A4,LegacyAvailability!$A$2:$A$25,0)) -> 1 | H4: =IF(C4=G4,0,1) -> 1
A5: M004 | B5: Synthetic meal configuration 04 | C5: 0 | D5: 46283.49 | E5: 18 | F5: Synthetic scenario | G5: =INDEX(LegacyAvailability!$B$2:$B$25,MATCH(A5,LegacyAvailability!$A$2:$A$25,0)) -> 1 | H5: =IF(C5=G5,0,1) -> 1
A6: M005 | B6: Synthetic meal configuration 05 | C6: 0 | D6: 46283.49 | E6: 14 | F6: Synthetic scenario | G6: =INDEX(LegacyAvailability!$B$2:$B$25,MATCH(A6,LegacyAvailability!$A$2:$A$25,0)) -> 1 | H6: =IF(C6=G6,0,1) -> 1
A7: M006 | B7: Synthetic meal configuration 06 | C7: 0 | D7: 46283.49 | E7: 15 | F7: Synthetic scenario | G7: =INDEX(LegacyAvailability!$B$2:$B$25,MATCH(A7,LegacyAvailability!$A$2:$A$25,0)) -> 1 | H7: =IF(C7=G7,0,1) -> 1
A8: M007 | B8: Synthetic meal configuration 07 | C8: 0 | D8: 46283.49 | E8: 16 | F8: Synthetic scenario | G8: =INDEX(LegacyAvailability!$B$2:$B$25,MATCH(A8,LegacyAvailability!$A$2:$A$25,0)) -> 1 | H8: =IF(C8=G8,0,1) -> 1
A9: M008 | B9: Synthetic meal configuration 08 | C9: 0 | D9: 46283.49 | E9: 17 | F9: Synthetic scenario | G9: =INDEX(LegacyAvailability!$B$2:$B$25,MATCH(A9,LegacyAvailability!$A$2:$A$25,0)) -> 1 | H9: =IF(C9=G9,0,1) -> 1
A10: M009 | B10: Synthetic meal configuration 09 | C10: 0 | D10: 46283.49 | E10: 18 | F10: Synthetic scenario | G10: =INDEX(LegacyAvailability!$B$2:$B$25,MATCH(A10,LegacyAvailability!$A$2:$A$25,0)) -> 1 | H10: =IF(C10=G10,0,1) -> 1
A11: M010 | B11: Synthetic meal configuration 10 | C11: 0 | D11: 46283.49 | E11: 14 | F11: Synthetic scenario | G11: =INDEX(LegacyAvailability!$B$2:$B$25,MATCH(A11,LegacyAvailability!$A$2:$A$25,0)) -> 1 | H11: =IF(C11=G11,0,1) -> 1
A12: M011 | B12: Synthetic meal configuration 11 | C12: 1 | D12: 46283.49 | E12: 15 | F12: Synthetic scenario | G12: =INDEX(LegacyAvailability!$B$2:$B$25,MATCH(A12,LegacyAvailability!$A$2:$A$25,0)) -> 1 | H12: =IF(C12=G12,0,1) -> 0
A13: M012 | B13: Synthetic meal configuration 12 | C13: 1 | D13: 46283.49 | E13: 16 | F13: Synthetic scenario | G13: =INDEX(LegacyAvailability!$B$2:$B$25,MATCH(A13,LegacyAvailability!$A$2:$A$25,0)) -> 1 | H13: =IF(C13=G13,0,1) -> 0
... A25: M024 | B25: Synthetic meal configuration 24 | C25: 1 | D25: 46283.49 | E25: 18 | F25: Synthetic scenario | G25: =INDEX(LegacyAvailability!$B$2:$B$25,MATCH(A25,LegacyAvailability!$A$2:$A$25,0)) -> 1 | H25: =IF(C25=G25,0,1) -> 0

Sheet Orders
A1: OrderID | B1: CustomerID | C1: CreatedAt | D1: Channel | E1: PromisedAt | F1: OrderStatus | G1: StoreID
A2: O001 | B2: C001 | C2: 46283.5 | D2: Web | E2: 46283.51 | F2: Completed | G2: SYN-01
A3: O002 | B3: C002 | C3: 46283.501 | D3: Third-party | E3: 46283.512 | F3: Completed | G3: SYN-01
A4: O003 | B4: C003 | C4: 46283.503 | D4: App | E4: 46283.513 | F4: Completed | G4: SYN-01
A5: O004 | B5: C004 | C5: 46283.504 | D5: Web | E5: 46283.515 | F5: Completed | G5: SYN-01
A6: O005 | B6: C005 | C6: 46283.506 | D6: Third-party | E6: 46283.516 | F6: Completed | G6: SYN-01
A7: O006 | B7: C006 | C7: 46283.507 | D7: App | E7: 46283.517 | F7: Completed | G7: SYN-01
A8: O007 | B8: C007 | C8: 46283.508 | D8: Web | E8: 46283.519 | F8: Completed | G8: SYN-01
A9: O008 | B9: C008 | C9: 46283.51 | D9: Third-party | E9: 46283.52 | F9: Completed | G9: SYN-01
A10: O009 | B10: C009 | C10: 46283.511 | D10: App | E10: 46283.522 | F10: Completed | G10: SYN-01
A11: O010 | B11: C010 | C11: 46283.512 | D11: Web | E11: 46283.523 | F11: Completed | G11: SYN-01
A12: O011 | B12: C011 | C12: 46283.514 | D12: Third-party | E12: 46283.524 | F12: Completed | G12: SYN-01
A13: O012 | B13: C012 | C13: 46283.515 | D13: App | E13: 46283.526 | F13: Completed | G13: SYN-01
... A31: O030 | B31: C006 | C31: 46283.54 | D31: App | E31: 46283.551 | F31: Completed | G31: SYN-01

Sheet OrderLines
A1: LineID | B1: OrderID | C1: SKU | D1: Qty | E1: UnitPrice | F1: LineAmount
A2: L001 | B2: O001 | C2: M001 | D2: 1 | E2: 15 | F2: =D2*E2 -> 15
A3: L002 | B3: O002 | C3: M002 | D3: 1 | E3: 16 | F3: =D3*E3 -> 16
A4: L003 | B4: O003 | C4: M003 | D4: 1 | E4: 17 | F4: =D4*E4 -> 17
A5: L004 | B5: O004 | C5: M004 | D5: 1 | E5: 18 | F5: =D5*E5 -> 18
A6: L005 | B6: O005 | C6: M005 | D6: 1 | E6: 14 | F6: =D6*E6 -> 14
A7: L006 | B7: O006 | C7: M006 | D7: 1 | E7: 15 | F7: =D7*E7 -> 15
A8: L007 | B8: O007 | C8: M011 | D8: 1 | E8: 15 | F8: =D8*E8 -> 15
A9: L008 | B9: O008 | C9: M012 | D9: 1 | E9: 16 | F9: =D9*E9 -> 16
A10: L009 | B10: O009 | C10: M013 | D10: 1 | E10: 17 | F10: =D10*E10 -> 17
A11: L010 | B11: O010 | C11: M014 | D11: 1 | E11: 18 | F11: =D11*E11 -> 18
A12: L011 | B12: O011 | C12: M015 | D12: 1 | E12: 14 | F12: =D12*E12 -> 14
A13: L012 | B13: O012 | C13: M016 | D13: 1 | E13: 15 | F13: =D13*E13 -> 15
... A41: L040 | B41: O030 | C41: M013 | D41: 1 | E41: 17 | F41: =D41*E41 -> 17

Sheet KitchenRuns
A1: RunID | B1: OrderID | C1: GateStatus | D1: RejectedAt | E1: ReentryStatus | F1: ReenteredAt | G1: ReadyAt | H1: HandoffAt | I1: ExtraLaborMin | J1: FoodWasteUSD | K1: JudgmentNote | L1: RecoveryChoice | M1: Consent | N1: Urgency | O1: PrepETAmin | P1: QueueMin | Q1: Constraint | R1: ExceptionID
A2: K001 | B2: O001 | C2: Rejected | D2: 46283.503 | E2: Rework | F2: 46283.509 | G2: 46283.519 | H2: 46283.519 | I2: 8 | J2: 4 | K2: Pickup deadline in 10 minutes; fresh prep takes 12. Guest asks whether to wait or cancel. | L2: Wait for fresh prep | M2: Customer agreed | N2: Pickup deadline | O2: 12 | P2: 5 | Q2: No substitution without consent | R2: E001
A3: K002 | B3: O002 | C3: Rejected | D3: 46283.505 | E3: Rework | F3: 46283.512 | G3: 46283.522 | H3: 46283.523 | I3: 10 | J3: 5 | K3: Guest permits some changes but flags an ingredient restriction. Manager must clarify safe choices; do not infer safety. | L3: Wait for fresh prep | M3: Customer agreed | N3: Pickup deadline | O3: 8 | P3: 6 | Q3: Ingredient restriction; human confirmation required | R3: E002
A4: K003 | B4: O003 | C4: Rejected | D4: 46283.506 | E4: Rework | F4: 46283.515 | G4: 46283.526 | H4: 46283.526 | I4: 12 | J4: 4 | K4: Driver waiting; two delayed orders compete for next prep slot. Weigh lateness and queue impact, not customer spend. | L4: Wait for fresh prep | M4: Customer agreed | N4: Driver waiting; competing delayed order | O4: 9 | P4: 7 | Q4: No substitution without consent | R4: E003
A5: K004 | B5: O004 | C5: Rejected | D5: 46283.508 | E5: Rework | F5: 46283.514 | G5: 46283.528 | H5: 46283.529 | I5: 9 | J5: 6 | K5: None | L5: Wait for fresh prep | M5: Customer agreed | N5: Pickup deadline | O5: 10 | P5: 8 | Q5: No substitution without consent | R5: E004
A6: K005 | B6: O005 | C6: Rejected | D6: 46283.509 | E6: Rework | F6: 46283.517 | G6: 46283.531 | H6: 46283.532 | I6: 11 | J6: 4 | K6: None | L6: Wait for fresh prep | M6: Customer agreed | N6: Pickup deadline | O6: 11 | P6: 9 | Q6: No substitution without consent | R6: E005
A7: K006 | B7: O006 | C7: Rejected | D7: 46283.51 | E7: Rework | F7: 46283.517 | G7: 46283.535 | H7: 46283.535 | I7: 10 | J7: 5 | K7: None | L7: Wait for fresh prep | M7: Customer agreed | N7: Pickup deadline | O7: 12 | P7: 10 | Q7: No substitution without consent | R7: E006
A8: K007 | B8: O007 | C8: Accepted | E8: Not required | G8: 46283.517 | H8: 46283.518 | I8: 0 | J8: 0 | K8: None | L8: Original meal | M8: Not needed | N8: Routine | O8: 0 | P8: 0 | Q8: None
A9: K008 | B9: O008 | C9: Accepted | E9: Not required | G9: 46283.519 | H9: 46283.519 | I9: 0 | J9: 0 | K9: None | L9: Original meal | M9: Not needed | N9: Routine | O9: 0 | P9: 0 | Q9: None
A10: K009 | B10: O009 | C10: Accepted | E10: Not required | G10: 46283.52 | H10: 46283.521 | I10: 0 | J10: 0 | K10: None | L10: Original meal | M10: Not needed | N10: Routine | O10: 0 | P10: 0 | Q10: None
A11: K010 | B11: O010 | C11: Accepted | E11: Not required | G11: 46283.522 | H11: 46283.522 | I11: 0 | J11: 0 | K11: None | L11: Original meal | M11: Not needed | N11: Routine | O11: 0 | P11: 0 | Q11: None
A12: K011 | B12: O011 | C12: Accepted | E12: Not required | G12: 46283.523 | H12: 46283.524 | I12: 0 | J12: 0 | K12: None | L12: Original meal | M12: Not needed | N12: Routine | O12: 0 | P12: 0 | Q12: None
A13: K012 | B13: O012 | C13: Accepted | E13: Not required | G13: 46283.524 | H13: 46283.525 | I13: 0 | J13: 0 | K13: None | L13: Original meal | M13: Not needed | N13: Routine | O13: 0 | P13: 0 | Q13: None
A14: K013 | B14: O013 | C14: Accepted | E14: Not required | G14: 46283.526 | H14: 46283.526 | I14: 0 | J14: 0 | K14: None | L14: Original meal | M14: Not needed | N14: Routine | O14: 0 | P14: 0 | Q14: None
A15: K014 | B15: O014 | C15: Accepted | E15: Not required | G15: 46283.527 | H15: 46283.528 | I15: 0 | J15: 0 | K15: None | L15: Original meal | M15: Not needed | N15: Routine | O15: 0 | P15: 0 | Q15: None
A16: K015 | B16: O015 | C16: Accepted | E16: Not required | G16: 46283.528 | H16: 46283.529 | I16: 0 | J16: 0 | K16: None | L16: Original meal | M16: Not needed | N16: Routine | O16: 0 | P16: 0 | Q16: None
A17: K016 | B17: O016 | C17: Accepted | E17: Not required | G17: 46283.53 | H17: 46283.531 | I17: 0 | J17: 0 | K17: None | L17: Original meal | M17: Not needed | N17: Routine | O17: 0 | P17: 0 | Q17: None
A18: K017 | B18: O017 | C18: Accepted | E18: Not required | G18: 46283.531 | H18: 46283.532 | I18: 0 | J18: 0 | K18: None | L18: Original meal | M18: Not needed | N18: Routine | O18: 0 | P18: 0 | Q18: None
A19: K018 | B19: O018 | C19: Accepted | E19: Not required | G19: 46283.533 | H19: 46283.533 | I19: 0 | J19: 0 | K19: None | L19: Original meal | M19: Not needed | N19: Routine | O19: 0 | P19: 0 | Q19: None
... A31: K030 | B31: O030 | C31: Accepted | E31: Not required | G31: 46283.549 | H31: 46283.55 | I31: 0 | J31: 0 | K31: None | L31: Original meal | M31: Not needed | N31: Routine | O31: 0 | P31: 0 | Q31: None

Sheet Payments
A1: PaymentID | B1: OrderID | C1: AuthorizedAt | D1: CapturedUSD | E1: RefundUSD | F1: NetUSD | G1: PostedAt
A2: P001 | B2: O001 | C2: 46283.5 | D2: 15 | E2: 3 | F2: =D2-E2 -> 12 | G2: 46283.519
A3: P002 | B3: O002 | C3: 46283.502 | D3: 16 | E3: 3 | F3: =D3-E3 -> 13 | G3: 46283.523
A4: P003 | B4: O003 | C4: 46283.503 | D4: 17 | E4: 4 | F4: =D4-E4 -> 13 | G4: 46283.526
A5: P004 | B5: O004 | C5: 46283.505 | D5: 18 | E5: 3 | F5: =D5-E5 -> 15 | G5: 46283.529
A6: P005 | B6: O005 | C6: 46283.506 | D6: 14 | E6: 4 | F6: =D6-E6 -> 10 | G6: 46283.532
A7: P006 | B7: O006 | C7: 46283.507 | D7: 15 | E7: 3 | F7: =D7-E7 -> 12 | G7: 46283.535
A8: P007 | B8: O007 | C8: 46283.509 | D8: 15 | E8: 0 | F8: =D8-E8 -> 15 | G8: 46283.518
A9: P008 | B9: O008 | C9: 46283.51 | D9: 16 | E9: 0 | F9: =D9-E9 -> 16 | G9: 46283.519
A10: P009 | B10: O009 | C10: 46283.511 | D10: 17 | E10: 0 | F10: =D10-E10 -> 17 | G10: 46283.521
A11: P010 | B11: O010 | C11: 46283.513 | D11: 18 | E11: 0 | F11: =D11-E11 -> 18 | G11: 46283.522
A12: P011 | B12: O011 | C12: 46283.514 | D12: 14 | E12: 0 | F12: =D12-E12 -> 14 | G12: 46283.524
A13: P012 | B13: O012 | C13: 46283.516 | D13: 15 | E13: 0 | F13: =D13-E13 -> 15 | G13: 46283.525
... A31: P030 | B31: O030 | C31: 46283.541 | D31: 31 | E31: 0 | F31: =D31-E31 -> 31 | G31: 46283.55

Sheet LegacyAvailability
A1: SKU | B1: SnapshotAvailable | C1: SnapshotAt | D1: Source | E1: EvidenceType
A2: M001 | B2: 1 | C2: 46282.917 | D2: Nightly channel cache | E2: Synthetic curveball
A3: M002 | B3: 1 | C3: 46282.917 | D3: Nightly channel cache | E3: Synthetic curveball
A4: M003 | B4: 1 | C4: 46282.917 | D4: Nightly channel cache | E4: Synthetic curveball
A5: M004 | B5: 1 | C5: 46282.917 | D5: Nightly channel cache | E5: Synthetic curveball
A6: M005 | B6: 1 | C6: 46282.917 | D6: Nightly channel cache | E6: Synthetic curveball
A7: M006 | B7: 1 | C7: 46282.917 | D7: Nightly channel cache | E7: Synthetic curveball
A8: M007 | B8: 1 | C8: 46282.917 | D8: Nightly channel cache | E8: Synthetic curveball
A9: M008 | B9: 1 | C9: 46282.917 | D9: Nightly channel cache | E9: Synthetic curveball
A10: M009 | B10: 1 | C10: 46282.917 | D10: Nightly channel cache | E10: Synthetic curveball
A11: M010 | B11: 1 | C11: 46282.917 | D11: Nightly channel cache | E11: Synthetic curveball
A12: M011 | B12: 1 | C12: 46282.917 | D12: Nightly channel cache | E12: Synthetic curveball
A13: M012 | B13: 1 | C13: 46282.917 | D13: Nightly channel cache | E13: Synthetic curveball
... A25: M024 | B25: 1 | C25: 46282.917 | D25: Nightly channel cache | E25: Synthetic curveball

Sheet Calculations
A1: OrderID | B1: GateStatus | C1: PromisedAt | D1: ReadyAt | E1: LateMinutes | F1: ExtraLaborMin | G1: LaborValueUSD | H1: FoodWasteUSD | I1: RefundUSD | J1: BurdenUSD
A2: =Orders!A2 -> O001 | B2: =INDEX(KitchenRuns!$C$2:$C$31,MATCH(A2,KitchenRuns!$B$2:$B$31,0)) -> Rejected | C2: =INDEX(Orders!$E$2:$E$31,MATCH(A2,Orders!$A$2:$A$31,0)) -> 46283.51 | D2: =INDEX(KitchenRuns!$G$2:$G$31,MATCH(A2,KitchenRuns!$B$2:$B$31,0)) -> 46283.519 | E2: =MAX(0,ROUND((D2-C2)*1440,0)) -> 12 | F2: =INDEX(KitchenRuns!$I$2:$I$31,MATCH(A2,KitchenRuns!$B$2:$B$31,0)) -> 8 | G2: =F2*Guide!$B$4 -> 3.2 | H2: =INDEX(KitchenRuns!$J$2:$J$31,MATCH(A2,KitchenRuns!$B$2:$B$31,0)) -> 4 | I2: =INDEX(Payments!$E$2:$E$31,MATCH(A2,Payments!$B$2:$B$31,0)) -> 3 | J2: =G2+H2+I2 -> 10.2
A3: =Orders!A3 -> O002 | B3: =INDEX(KitchenRuns!$C$2:$C$31,MATCH(A3,KitchenRuns!$B$2:$B$31,0)) -> Rejected | C3: =INDEX(Orders!$E$2:$E$31,MATCH(A3,Orders!$A$2:$A$31,0)) -> 46283.512 | D3: =INDEX(KitchenRuns!$G$2:$G$31,MATCH(A3,KitchenRuns!$B$2:$B$31,0)) -> 46283.522 | E3: =MAX(0,ROUND((D3-C3)*1440,0)) -> 15 | F3: =INDEX(KitchenRuns!$I$2:$I$31,MATCH(A3,KitchenRuns!$B$2:$B$31,0)) -> 10 | G3: =F3*Guide!$B$4 -> 4 | H3: =INDEX(KitchenRuns!$J$2:$J$31,MATCH(A3,KitchenRuns!$B$2:$B$31,0)) -> 5 | I3: =INDEX(Payments!$E$2:$E$31,MATCH(A3,Payments!$B$2:$B$31,0)) -> 3 | J3: =G3+H3+I3 -> 12
A4: =Orders!A4 -> O003 | B4: =INDEX(KitchenRuns!$C$2:$C$31,MATCH(A4,KitchenRuns!$B$2:$B$31,0)) -> Rejected | C4: =INDEX(Orders!$E$2:$E$31,MATCH(A4,Orders!$A$2:$A$31,0)) -> 46283.513 | D4: =INDEX(KitchenRuns!$G$2:$G$31,MATCH(A4,KitchenRuns!$B$2:$B$31,0)) -> 46283.526 | E4: =MAX(0,ROUND((D4-C4)*1440,0)) -> 18 | F4: =INDEX(KitchenRuns!$I$2:$I$31,MATCH(A4,KitchenRuns!$B$2:$B$31,0)) -> 12 | G4: =F4*Guide!$B$4 -> 4.8 | H4: =INDEX(KitchenRuns!$J$2:$J$31,MATCH(A4,KitchenRuns!$B$2:$B$31,0)) -> 4 | I4: =INDEX(Payments!$E$2:$E$31,MATCH(A4,Payments!$B$2:$B$31,0)) -> 4 | J4: =G4+H4+I4 -> 12.8
A5: =Orders!A5 -> O004 | B5: =INDEX(KitchenRuns!$C$2:$C$31,MATCH(A5,KitchenRuns!$B$2:$B$31,0)) -> Rejected | C5: =INDEX(Orders!$E$2:$E$31,MATCH(A5,Orders!$A$2:$A$31,0)) -> 46283.515 | D5: =INDEX(KitchenRuns!$G$2:$G$31,MATCH(A5,KitchenRuns!$B$2:$B$31,0)) -> 46283.528 | E5: =MAX(0,ROUND((D5-C5)*1440,0)) -> 20 | F5: =INDEX(KitchenRuns!$I$2:$I$31,MATCH(A5,KitchenRuns!$B$2:$B$31,0)) -> 9 | G5: =F5*Guide!$B$4 -> 3.6 | H5: =INDEX(KitchenRuns!$J$2:$J$31,MATCH(A5,KitchenRuns!$B$2:$B$31,0)) -> 6 | I5: =INDEX(Payments!$E$2:$E$31,MATCH(A5,Payments!$B$2:$B$31,0)) -> 3 | J5: =G5+H5+I5 -> 12.6
A6: =Orders!A6 -> O005 | B6: =INDEX(KitchenRuns!$C$2:$C$31,MATCH(A6,KitchenRuns!$B$2:$B$31,0)) -> Rejected | C6: =INDEX(Orders!$E$2:$E$31,MATCH(A6,Orders!$A$2:$A$31,0)) -> 46283.516 | D6: =INDEX(KitchenRuns!$G$2:$G$31,MATCH(A6,KitchenRuns!$B$2:$B$31,0)) -> 46283.531 | E6: =MAX(0,ROUND((D6-C6)*1440,0)) -> 22 | F6: =INDEX(KitchenRuns!$I$2:$I$31,MATCH(A6,KitchenRuns!$B$2:$B$31,0)) -> 11 | G6: =F6*Guide!$B$4 -> 4.4 | H6: =INDEX(KitchenRuns!$J$2:$J$31,MATCH(A6,KitchenRuns!$B$2:$B$31,0)) -> 4 | I6: =INDEX(Payments!$E$2:$E$31,MATCH(A6,Payments!$B$2:$B$31,0)) -> 4 | J6: =G6+H6+I6 -> 12.4
A7: =Orders!A7 -> O006 | B7: =INDEX(KitchenRuns!$C$2:$C$31,MATCH(A7,KitchenRuns!$B$2:$B$31,0)) -> Rejected | C7: =INDEX(Orders!$E$2:$E$31,MATCH(A7,Orders!$A$2:$A$31,0)) -> 46283.517 | D7: =INDEX(KitchenRuns!$G$2:$G$31,MATCH(A7,KitchenRuns!$B$2:$B$31,0)) -> 46283.535 | E7: =MAX(0,ROUND((D7-C7)*1440,0)) -> 25 | F7: =INDEX(KitchenRuns!$I$2:$I$31,MATCH(A7,KitchenRuns!$B$2:$B$31,0)) -> 10 | G7: =F7*Guide!$B$4 -> 4 | H7: =INDEX(KitchenRuns!$J$2:$J$31,MATCH(A7,KitchenRuns!$B$2:$B$31,0)) -> 5 | I7: =INDEX(Payments!$E$2:$E$31,MATCH(A7,Payments!$B$2:$B$31,0)) -> 3 | J7: =G7+H7+I7 -> 12
A8: =Orders!A8 -> O007 | B8: =INDEX(KitchenRuns!$C$2:$C$31,MATCH(A8,KitchenRuns!$B$2:$B$31,0)) -> Accepted | C8: =INDEX(Orders!$E$2:$E$31,MATCH(A8,Orders!$A$2:$A$31,0)) -> 46283.519 | D8: =INDEX(KitchenRuns!$G$2:$G$31,MATCH(A8,KitchenRuns!$B$2:$B$31,0)) -> 46283.517 | E8: =MAX(0,ROUND((D8-C8)*1440,0)) -> 0 | F8: =INDEX(KitchenRuns!$I$2:$I$31,MATCH(A8,KitchenRuns!$B$2:$B$31,0)) -> 0 | G8: =F8*Guide!$B$4 -> 0 | H8: =INDEX(KitchenRuns!$J$2:$J$31,MATCH(A8,KitchenRuns!$B$2:$B$31,0)) -> 0 | I8: =INDEX(Payments!$E$2:$E$31,MATCH(A8,Payments!$B$2:$B$31,0)) -> 0 | J8: =G8+H8+I8 -> 0
A9: =Orders!A9 -> O008 | B9: =INDEX(KitchenRuns!$C$2:$C$31,MATCH(A9,KitchenRuns!$B$2:$B$31,0)) -> Accepted | C9: =INDEX(Orders!$E$2:$E$31,MATCH(A9,Orders!$A$2:$A$31,0)) -> 46283.52 | D9: =INDEX(KitchenRuns!$G$2:$G$31,MATCH(A9,KitchenRuns!$B$2:$B$31,0)) -> 46283.519 | E9: =MAX(0,ROUND((D9-C9)*1440,0)) -> 0 | F9: =INDEX(KitchenRuns!$I$2:$I$31,MATCH(A9,KitchenRuns!$B$2:$B$31,0)) -> 0 | G9: =F9*Guide!$B$4 -> 0 | H9: =INDEX(KitchenRuns!$J$2:$J$31,MATCH(A9,KitchenRuns!$B$2:$B$31,0)) -> 0 | I9: =INDEX(Payments!$E$2:$E$31,MATCH(A9,Payments!$B$2:$B$31,0)) -> 0 | J9: =G9+H9+I9 -> 0
A10: =Orders!A10 -> O009 | B10: =INDEX(KitchenRuns!$C$2:$C$31,MATCH(A10,KitchenRuns!$B$2:$B$31,0)) -> Accepted | C10: =INDEX(Orders!$E$2:$E$31,MATCH(A10,Orders!$A$2:$A$31,0)) -> 46283.522 | D10: =INDEX(KitchenRuns!$G$2:$G$31,MATCH(A10,KitchenRuns!$B$2:$B$31,0)) -> 46283.52 | E10: =MAX(0,ROUND((D10-C10)*1440,0)) -> 0 | F10: =INDEX(KitchenRuns!$I$2:$I$31,MATCH(A10,KitchenRuns!$B$2:$B$31,0)) -> 0 | G10: =F10*Guide!$B$4 -> 0 | H10: =INDEX(KitchenRuns!$J$2:$J$31,MATCH(A10,KitchenRuns!$B$2:$B$31,0)) -> 0 | I10: =INDEX(Payments!$E$2:$E$31,MATCH(A10,Payments!$B$2:$B$31,0)) -> 0 | J10: =G10+H10+I10 -> 0
A11: =Orders!A11 -> O010 | B11: =INDEX(KitchenRuns!$C$2:$C$31,MATCH(A11,KitchenRuns!$B$2:$B$31,0)) -> Accepted | C11: =INDEX(Orders!$E$2:$E$31,MATCH(A11,Orders!$A$2:$A$31,0)) -> 46283.523 | D11: =INDEX(KitchenRuns!$G$2:$G$31,MATCH(A11,KitchenRuns!$B$2:$B$31,0)) -> 46283.522 | E11: =MAX(0,ROUND((D11-C11)*1440,0)) -> 0 | F11: =INDEX(KitchenRuns!$I$2:$I$31,MATCH(A11,KitchenRuns!$B$2:$B$31,0)) -> 0 | G11: =F11*Guide!$B$4 -> 0 | H11: =INDEX(KitchenRuns!$J$2:$J$31,MATCH(A11,KitchenRuns!$B$2:$B$31,0)) -> 0 | I11: =INDEX(Payments!$E$2:$E$31,MATCH(A11,Payments!$B$2:$B$31,0)) -> 0 | J11: =G11+H11+I11 -> 0
A12: =Orders!A12 -> O011 | B12: =INDEX(KitchenRuns!$C$2:$C$31,MATCH(A12,KitchenRuns!$B$2:$B$31,0)) -> Accepted | C12: =INDEX(Orders!$E$2:$E$31,MATCH(A12,Orders!$A$2:$A$31,0)) -> 46283.524 | D12: =INDEX(KitchenRuns!$G$2:$G$31,MATCH(A12,KitchenRuns!$B$2:$B$31,0)) -> 46283.523 | E12: =MAX(0,ROUND((D12-C12)*1440,0)) -> 0 | F12: =INDEX(KitchenRuns!$I$2:$I$31,MATCH(A12,KitchenRuns!$B$2:$B$31,0)) -> 0 | G12: =F12*Guide!$B$4 -> 0 | H12: =INDEX(KitchenRuns!$J$2:$J$31,MATCH(A12,KitchenRuns!$B$2:$B$31,0)) -> 0 | I12: =INDEX(Payments!$E$2:$E$31,MATCH(A12,Payments!$B$2:$B$31,0)) -> 0 | J12: =G12+H12+I12 -> 0
A13: =Orders!A13 -> O012 | B13: =INDEX(KitchenRuns!$C$2:$C$31,MATCH(A13,KitchenRuns!$B$2:$B$31,0)) -> Accepted | C13: =INDEX(Orders!$E$2:$E$31,MATCH(A13,Orders!$A$2:$A$31,0)) -> 46283.526 | D13: =INDEX(KitchenRuns!$G$2:$G$31,MATCH(A13,KitchenRuns!$B$2:$B$31,0)) -> 46283.524 | E13: =MAX(0,ROUND((D13-C13)*1440,0)) -> 0 | F13: =INDEX(KitchenRuns!$I$2:$I$31,MATCH(A13,KitchenRuns!$B$2:$B$31,0)) -> 0 | G13: =F13*Guide!$B$4 -> 0 | H13: =INDEX(KitchenRuns!$J$2:$J$31,MATCH(A13,KitchenRuns!$B$2:$B$31,0)) -> 0 | I13: =INDEX(Payments!$E$2:$E$31,MATCH(A13,Payments!$B$2:$B$31,0)) -> 0 | J13: =G13+H13+I13 -> 0
... A31: =Orders!A31 -> O030 | B31: =INDEX(KitchenRuns!$C$2:$C$31,MATCH(A31,KitchenRuns!$B$2:$B$31,0)) -> Accepted | C31: =INDEX(Orders!$E$2:$E$31,MATCH(A31,Orders!$A$2:$A$31,0)) -> 46283.551 | D31: =INDEX(KitchenRuns!$G$2:$G$31,MATCH(A31,KitchenRuns!$B$2:$B$31,0)) -> 46283.549 | E31: =MAX(0,ROUND((D31-C31)*1440,0)) -> 0 | F31: =INDEX(KitchenRuns!$I$2:$I$31,MATCH(A31,KitchenRuns!$B$2:$B$31,0)) -> 0 | G31: =F31*Guide!$B$4 -> 0 | H31: =INDEX(KitchenRuns!$J$2:$J$31,MATCH(A31,KitchenRuns!$B$2:$B$31,0)) -> 0 | I31: =INDEX(Payments!$E$2:$E$31,MATCH(A31,Payments!$B$2:$B$31,0)) -> 0 | J31: =G31+H31+I31 -> 0

Sheet Guide
A1: Topic | B1: Definition / source
A2: Synthetic scope | B2: One hypothetical store SYN-01; 30 orders on 2026-09-18. Every row is synthetic. No real customer or restaurant data.
A3: Units | B3: USD; durations in minutes. Timestamps use local restaurant time (America/New_York) without timezone conversion.
A4: Labor cost per minute | B4: 0.4
A5: Labor assumption | B5: Illustrative loaded rate $24/hour. Models capacity consumed, not automatically additional payroll.
A6: Summary burden | B6: Discarded partial prep + labor time value + goodwill refunds. Do not add net receipts or gross sales to this number.
A7: Data grain | B7: Customers: guest; MenuItems: configuration; Orders: order; OrderLines: requested line; KitchenRuns: one order lifecycle; Payments: capture/refund summary; LegacyAvailability: independent snapshot/configuration.
A8: Keys | B8: CustomerID → Orders; OrderID → lines/runs/payments; SKU → MenuItems. Legacy SKU matches for comparison only; do not overwrite discrepancies.
A9: Status history | B9: Orders are Completed at final snapshot. KitchenRuns preserves Rejected → Rework via separate status and timestamp fields.
A10: Availability assumption | B10: CurrentAvailable=0: critical ingredient prevents completing this configuration until fresh prep. 1: fulfillable. It is not a quantity or reservation model.
A11: Food waste assumption | B11: Partial base prep begins before D2 checks the critical ingredient. Recovery discards some prep, recorded in FoodWasteUSD.
A12: Ready versus handoff | B12: Lateness is ReadyAt minus PromisedAt, floored at zero; handoff follows one minute later. PromisedAt is readiness promise.
A13: Clean generation | B13: Clean linked data first; deliberate changes then applied. The private changes CSV records every mutation. Arithmetic remains formula-driven.
A14: Observed paths | B14: Six D2 rejections recover and complete. D1 failure, D3 cancellation and D4 quality rejection are drawn but unexercised alternatives.
A15: Judgment inputs | B15: Urgency, PrepETAmin, QueueMin, Constraint/Consent. A manager confirms safety and the recovery choice; AI does not infer allergy safety.
A16: Source freshness | B16: Nightly snapshot 2026-09-17 22:00; current kitchen check 2026-09-18 11:45. Overnight cadence is the chosen curveball, not a researched Sweetgreen fact.
... A23: Generation tool | B23: Deterministic script, not Gemini. Use handoff prompts if the instructor specifically requires the default Gemini exercise.
