Workbook

Sheet Summary
A1: Sweetgreen Lab 1 sandbox | B1: Value | C1: Definition
A2: Scenario | B2: Synthetic | C2: Gemini-generated source tables, 18 September 2026
A3: Orders | B3: =COUNTA(Orders!A2:A31) -> 30 | C3: All accepted orders
A4: Exception orders | B4: =COUNTIF(Calculations!B2:B31,">0") -> 6 | C4: Orders with at least one BLOCKED kitchen attempt
A5: Exception rate | B5: =B4/B3 -> 0.2 | C5: Exception orders / total orders
A6: Availability mismatches | B6: =SUM(Availability!F2:F25) -> 10 | C6: Cached and current availability disagree
A7: Extra labor minutes | B7: =SUM(Calculations!F2:F31) -> 60 | C7: Recovery effort across all kitchen attempts
A8: Labor value USD | B8: =SUM(Calculations!G2:G31) -> 24 | C8: Minutes / 60 x assumed $24/hour
A9: Goodwill refunds USD | B9: =SUM(Calculations!H2:H31) -> 20 | C9: Partial refunds on completed orders
A10: Modeled burden USD | B10: =B8+B9 -> 44 | C10: Labor capacity value plus refunds; excludes food waste
A11: Readiness late minutes | B11: =SUM(Calculations!E2:E31) -> 112 | C11: Lateness summed across all orders, floored at zero
A12: Mean affected lateness | B12: =SUMIF(Calculations!B2:B31,">0",Calculations!E2:E31)/B4 -> 18.666667 | C12: Readiness lateness among exception orders
A13: Capture discrepancy USD | B13: =SUM(Calculations!J2:J31) -> 0 | C13: Sum of absolute per-order capture-to-line differences
A14: Interpretation | B14: Illustrative | C14: Not measured Sweetgreen performance or guaranteed savings

Sheet Customers
A1: customer_id | B1: segment | C1: urgency | D1: restriction_note
A2: C001 | B2: Student | C2: High | D2: None
A3: C002 | B3: Faculty | C3: High | D3: None
A4: C003 | B4: Student | C4: High | D4: None
A5: C004 | B5: Staff | C5: Medium | D5: None
A6: C005 | B6: Student | C6: Medium | D6: None
A7: C006 | B7: Faculty | C7: Low | D7: None
A8: C007 | B8: Student | C8: Low | D8: None
A9: C008 | B9: Student | C9: Low | D9: None
A10: C009 | B10: Staff | C10: Low | D10: None
A11: C010 | B11: Student | C11: Medium | D11: None
A12: C011 | B12: Faculty | C12: Low | D12: None
... A31: C030 | B31: Student | C31: Low | D31: None

Sheet MenuItems
A1: item_id | B1: item_name | C1: price
A2: M001 | B2: Harvest Bowl | C2: 13.5
A3: M002 | B3: Shroomami | C3: 13
A4: M003 | B4: Hot Honey Chicken | C4: 14.5
A5: M004 | B5: Kale Caesar | C5: 12.5
A6: M005 | B6: Crispy Rice Bowl | C6: 14
A7: M006 | B7: Guacamole Greens | C7: 13.5
A8: M007 | B8: Fish Taco Bowl | C8: 15
A9: M008 | B9: Super Green Goddess | C9: 13
A10: M009 | B10: Chicken Avocado Ranch | C10: 14.5
A11: M010 | B11: Hummus Tahina | C11: 12
A12: M011 | B12: Peach Goat Cheese Salad | C12: 13.5
A13: M012 | B13: Balsamic Chicken Bowl | C13: 13
... A25: M024 | B25: Citrus Salmon Bowl | C25: 15.5

Sheet Availability
A1: item_id | B1: snapshot_at | C1: snapshot_available | D1: current_at | E1: current_available | F1: Mismatch (derived)
A2: M001 | B2: 46283 | C2: TRUE | D2: 46283.458 | E2: FALSE | F2: =IF(C2=E2,0,1) -> 1
A3: M002 | B3: 46283 | C3: TRUE | D3: 46283.458 | E3: FALSE | F3: =IF(C3=E3,0,1) -> 1
A4: M003 | B4: 46283 | C4: TRUE | D4: 46283.458 | E4: FALSE | F4: =IF(C4=E4,0,1) -> 1
A5: M004 | B5: 46283 | C5: TRUE | D5: 46283.458 | E5: FALSE | F5: =IF(C5=E5,0,1) -> 1
A6: M005 | B6: 46283 | C6: TRUE | D6: 46283.458 | E6: FALSE | F6: =IF(C6=E6,0,1) -> 1
A7: M006 | B7: 46283 | C7: TRUE | D7: 46283.458 | E7: FALSE | F7: =IF(C7=E7,0,1) -> 1
A8: M007 | B8: 46283 | C8: TRUE | D8: 46283.458 | E8: FALSE | F8: =IF(C8=E8,0,1) -> 1
A9: M008 | B9: 46283 | C9: TRUE | D9: 46283.458 | E9: FALSE | F9: =IF(C9=E9,0,1) -> 1
A10: M009 | B10: 46283 | C10: TRUE | D10: 46283.458 | E10: FALSE | F10: =IF(C10=E10,0,1) -> 1
A11: M010 | B11: 46283 | C11: TRUE | D11: 46283.458 | E11: FALSE | F11: =IF(C11=E11,0,1) -> 1
A12: M011 | B12: 46283 | C12: TRUE | D12: 46283.458 | E12: TRUE | F12: =IF(C12=E12,0,1) -> 0
A13: M012 | B13: 46283 | C13: TRUE | D13: 46283.458 | E13: TRUE | F13: =IF(C13=E13,0,1) -> 0
... A25: M024 | B25: 46283 | C25: TRUE | D25: 46283.458 | E25: TRUE | F25: =IF(C25=E25,0,1) -> 0

Sheet Orders
A1: order_id | B1: customer_id | C1: accepted_at | D1: promised_at | E1: completed_at | F1: status
A2: O001 | B2: C001 | C2: 46283.459 | D2: 46283.469 | E2: 46283.477 | F2: COMPLETED
A3: O002 | B3: C002 | C3: 46283.46 | D3: 46283.469 | E3: 46283.48 | F3: COMPLETED
A4: O003 | B4: C003 | C4: 46283.46 | D4: 46283.47 | E4: 46283.482 | F4: COMPLETED
A5: O004 | B5: C004 | C5: 46283.461 | D5: 46283.471 | E5: 46283.485 | F5: COMPLETED
A6: O005 | B6: C005 | C6: 46283.462 | D6: 46283.472 | E6: 46283.487 | F6: COMPLETED
A7: O006 | B7: C006 | C7: 46283.463 | D7: 46283.472 | E7: 46283.49 | F7: COMPLETED
A8: O007 | B8: C007 | C8: 46283.463 | D8: 46283.473 | E8: 46283.472 | F8: COMPLETED
A9: O008 | B9: C008 | C9: 46283.464 | D9: 46283.474 | E9: 46283.472 | F9: COMPLETED
A10: O009 | B10: C009 | C10: 46283.465 | D10: 46283.474 | E10: 46283.473 | F10: COMPLETED
A11: O010 | B11: C010 | C11: 46283.465 | D11: 46283.475 | E11: 46283.474 | F11: COMPLETED
A12: O011 | B12: C011 | C12: 46283.466 | D12: 46283.476 | E12: 46283.474 | F12: COMPLETED
A13: O012 | B13: C012 | C13: 46283.467 | D13: 46283.476 | E13: 46283.475 | F13: COMPLETED
... A31: O030 | B31: C030 | C31: 46283.479 | D31: 46283.489 | E31: 46283.488 | F31: COMPLETED

Sheet OrderLines
A1: line_id | B1: order_id | C1: item_id | D1: qty | E1: unit_price | F1: final_item_id | G1: change_agreed_at | H1: consent | I1: Line total USD
A2: L001 | B2: O001 | C2: M001 | D2: 1 | E2: 13.5 | F2: M011 | G2: 46283.466 | H2: TRUE | I2: =D2*E2 -> 13.5
A3: L002 | B3: O002 | C3: M002 | D3: 1 | E3: 13 | F3: M012 | G3: 46283.467 | H3: TRUE | I3: =D3*E3 -> 13
A4: L003 | B4: O003 | C4: M003 | D4: 1 | E4: 14.5 | F4: M013 | G4: 46283.467 | H4: TRUE | I4: =D4*E4 -> 14.5
A5: L004 | B5: O004 | C5: M004 | D5: 1 | E5: 12.5 | F5: M014 | G5: 46283.468 | H5: TRUE | I5: =D5*E5 -> 12.5
A6: L005 | B6: O005 | C6: M005 | D6: 1 | E6: 14 | F6: M015 | G6: 46283.469 | H6: TRUE | I6: =D6*E6 -> 14
A7: L006 | B7: O006 | C7: M006 | D7: 1 | E7: 13.5 | F7: M016 | G7: 46283.469 | H7: TRUE | I7: =D7*E7 -> 13.5
A8: L007 | B8: O007 | C8: M011 | D8: 1 | E8: 13.5 | F8: M011 | I8: =D8*E8 -> 13.5
A9: L008 | B9: O008 | C9: M012 | D9: 1 | E9: 13 | F9: M012 | I9: =D9*E9 -> 13
A10: L009 | B10: O009 | C10: M013 | D10: 1 | E10: 14.5 | F10: M013 | I10: =D10*E10 -> 14.5
A11: L010 | B11: O010 | C11: M014 | D11: 1 | E11: 12.5 | F11: M014 | I11: =D11*E11 -> 12.5
A12: L011 | B12: O011 | C12: M015 | D12: 1 | E12: 14 | F12: M015 | I12: =D12*E12 -> 14
A13: L012 | B13: O012 | C13: M016 | D13: 1 | E13: 13.5 | F13: M016 | I13: =D13*E13 -> 13.5
A14: L013 | B14: O013 | C14: M017 | D14: 1 | E14: 15 | F14: M017 | I14: =D14*E14 -> 15
A15: L014 | B15: O014 | C15: M018 | D15: 1 | E15: 13 | F15: M018 | I15: =D15*E15 -> 13
A16: L015 | B16: O015 | C16: M019 | D16: 1 | E16: 14.5 | F16: M019 | I16: =D16*E16 -> 14.5
A17: L016 | B17: O016 | C17: M020 | D17: 1 | E17: 12 | F17: M020 | I17: =D17*E17 -> 12
A18: L017 | B18: O017 | C18: M021 | D18: 1 | E18: 13 | F18: M021 | I18: =D18*E18 -> 13
A19: L018 | B19: O018 | C19: M022 | D19: 1 | E19: 12.5 | F19: M022 | I19: =D19*E19 -> 12.5
... A37: L036 | B37: O030 | C37: M012 | D37: 1 | E37: 13 | F37: M012 | I37: =D37*E37 -> 13

Sheet KitchenRuns
A1: run_id | B1: order_id | C1: attempt_no | D1: checked_at | E1: status | F1: exception_id | G1: reason | H1: staff_role | I1: extra_labor_min | J1: prep_started_at | K1: ready_at | L1: recovery_note
A2: R001 | B2: O001 | C2: 1 | D2: 46283.46 | E2: BLOCKED | F2: E001 | G2: Item M001 unavail at kitchen station | H2: Shift Supervisor | I2: 10 | L2: Customer C001 flagged high urgency due to class schedule; estimated +6 min prep ETA and queue impact; offered M011 replacement; verbal consent given.
A3: R002 | B3: O001 | C3: 2 | D3: 46283.466 | E3: SUCCESS | H3: Prep Line Staff | I3: 0 | J3: 46283.467 | K3: 46283.477 | L3: Item replacement M011 prepped.
A4: R003 | B4: O002 | C4: 1 | D4: 46283.46 | E4: BLOCKED | F4: E002 | G4: Item M002 unavail at kitchen station | H4: Shift Supervisor | I4: 10 | L4: Customer C002 flagged high urgency for faculty meeting; estimated +8 min prep ETA and line impact; offered M012 replacement; verbal consent given.
A5: R004 | B5: O002 | C5: 2 | D5: 46283.467 | E5: SUCCESS | H5: Prep Line Staff | I5: 0 | J5: 46283.467 | K5: 46283.48 | L5: Item replacement M012 prepped.
A6: R005 | B6: O003 | C6: 1 | D6: 46283.461 | E6: BLOCKED | F6: E003 | G6: Item M003 unavail at kitchen station | H6: Shift Supervisor | I6: 10 | L6: Customer C003 flagged high urgency for exam; estimated +10 min prep ETA and queue impact; offered M013 replacement; verbal consent given.
A7: R006 | B7: O003 | C7: 2 | D7: 46283.468 | E7: SUCCESS | H7: Prep Line Staff | I7: 0 | J7: 46283.468 | K7: 46283.482 | L7: Item replacement M013 prepped.
A8: R007 | B8: O004 | C8: 1 | D8: 46283.462 | E8: BLOCKED | F8: E004 | G8: Item M004 unavail at kitchen station | H8: Prep Line Staff | I8: 10 | L8: Routine replacement agreed: M004 replaced with M014.
A9: R008 | B9: O004 | C9: 2 | D9: 46283.468 | E9: SUCCESS | H9: Prep Line Staff | I9: 0 | J9: 46283.469 | K9: 46283.485 | L9: Item replacement M014 prepped.
A10: R009 | B10: O005 | C10: 1 | D10: 46283.463 | E10: BLOCKED | F10: E005 | G10: Item M005 unavail at kitchen station | H10: Prep Line Staff | I10: 10 | L10: Routine replacement agreed: M005 replaced with M015.
A11: R010 | B11: O005 | C11: 2 | D11: 46283.469 | E11: SUCCESS | H11: Prep Line Staff | I11: 0 | J11: 46283.469 | K11: 46283.487 | L11: Item replacement M015 prepped.
A12: R011 | B12: O006 | C12: 1 | D12: 46283.463 | E12: BLOCKED | F12: E006 | G12: Item M006 unavail at kitchen station | H12: Prep Line Staff | I12: 10 | L12: Routine replacement agreed: M006 replaced with M016.
A13: R012 | B13: O006 | C13: 2 | D13: 46283.47 | E13: SUCCESS | H13: Prep Line Staff | I13: 0 | J13: 46283.47 | K13: 46283.49 | L13: Item replacement M016 prepped.
A14: R013 | B14: O007 | C14: 1 | D14: 46283.464 | E14: SUCCESS | H14: Prep Line Staff | I14: 0 | J14: 46283.464 | K14: 46283.468 | L14: Standard preparation.
A15: R014 | B15: O008 | C15: 1 | D15: 46283.465 | E15: SUCCESS | H15: Prep Line Staff | I15: 0 | J15: 46283.465 | K15: 46283.469 | L15: Standard preparation.
A16: R015 | B16: O009 | C16: 1 | D16: 46283.465 | E16: SUCCESS | H16: Prep Line Staff | I16: 0 | J16: 46283.466 | K16: 46283.47 | L16: Standard preparation.
A17: R016 | B17: O010 | C17: 1 | D17: 46283.466 | E17: SUCCESS | H17: Prep Line Staff | I17: 0 | J17: 46283.466 | K17: 46283.47 | L17: Standard preparation.
A18: R017 | B18: O011 | C18: 1 | D18: 46283.467 | E18: SUCCESS | H18: Prep Line Staff | I18: 0 | J18: 46283.467 | K18: 46283.471 | L18: Standard preparation.
A19: R018 | B19: O012 | C19: 1 | D19: 46283.467 | E19: SUCCESS | H19: Prep Line Staff | I19: 0 | J19: 46283.468 | K19: 46283.472 | L19: Standard preparation.
A20: R019 | B20: O013 | C20: 1 | D20: 46283.468 | E20: SUCCESS | H20: Prep Line Staff | I20: 0 | J20: 46283.468 | K20: 46283.473 | L20: Standard preparation.
A21: R020 | B21: O014 | C21: 1 | D21: 46283.469 | E21: SUCCESS | H21: Prep Line Staff | I21: 0 | J21: 46283.469 | K21: 46283.473 | L21: Standard preparation.
A22: R021 | B22: O015 | C22: 1 | D22: 46283.469 | E22: SUCCESS | H22: Prep Line Staff | I22: 0 | J22: 46283.47 | K22: 46283.474 | L22: Standard preparation.
A23: R022 | B23: O016 | C23: 1 | D23: 46283.47 | E23: SUCCESS | H23: Prep Line Staff | I23: 0 | J23: 46283.47 | K23: 46283.475 | L23: Standard preparation.
A24: R023 | B24: O017 | C24: 1 | D24: 46283.471 | E24: SUCCESS | H24: Prep Line Staff | I24: 0 | J24: 46283.471 | K24: 46283.475 | L24: Standard preparation.
... A37: R036 | B37: O030 | C37: 1 | D37: 46283.48 | E37: SUCCESS | H37: Prep Line Staff | I37: 0 | J37: 46283.48 | K37: 46283.484 | L37: Standard preparation.

Sheet Payments
A1: payment_id | B1: order_id | C1: event_at | D1: type | E1: amount | F1: status
A2: P001 | B2: O001 | C2: 46283.459 | D2: CAPTURE | E2: 13.5 | F2: SETTLED
A3: P002 | B3: O002 | C3: 46283.46 | D3: CAPTURE | E3: 13 | F3: SETTLED
A4: P003 | B4: O003 | C4: 46283.46 | D4: CAPTURE | E4: 14.5 | F4: SETTLED
A5: P004 | B5: O004 | C5: 46283.461 | D5: CAPTURE | E5: 12.5 | F5: SETTLED
A6: P005 | B6: O005 | C6: 46283.462 | D6: CAPTURE | E6: 14 | F6: SETTLED
A7: P006 | B7: O006 | C7: 46283.463 | D7: CAPTURE | E7: 13.5 | F7: SETTLED
A8: P007 | B8: O007 | C8: 46283.463 | D8: CAPTURE | E8: 13.5 | F8: SETTLED
A9: P008 | B9: O008 | C9: 46283.464 | D9: CAPTURE | E9: 13 | F9: SETTLED
A10: P009 | B10: O009 | C10: 46283.465 | D10: CAPTURE | E10: 14.5 | F10: SETTLED
A11: P010 | B11: O010 | C11: 46283.465 | D11: CAPTURE | E11: 12.5 | F11: SETTLED
A12: P011 | B12: O011 | C12: 46283.466 | D12: CAPTURE | E12: 14 | F12: SETTLED
A13: P012 | B13: O012 | C13: 46283.467 | D13: CAPTURE | E13: 13.5 | F13: SETTLED
... A37: P036 | B37: O006 | C37: 46283.491 | D37: REFUND_GOODWILL | E37: 4 | F37: SETTLED

Sheet Calculations
A1: Order ID | B1: Exception count | C1: Promised at UTC | D1: Ready at UTC | E1: Late minutes | F1: Extra labor min | G1: Labor value USD | H1: Refunds USD | I1: Burden USD | J1: Absolute capture difference USD
A2: =Orders!A2 -> O001 | B2: =COUNTIFS(KitchenRuns!$B$2:$B$37,A2,KitchenRuns!$E$2:$E$37,"BLOCKED") -> 1 | C2: =Orders!D2 -> 46283.469 | D2: =SUMIFS(KitchenRuns!$K$2:$K$37,KitchenRuns!$B$2:$B$37,A2,KitchenRuns!$E$2:$E$37,"SUCCESS") -> 46283.477 | E2: =MAX(0,ROUND((D2-C2)*1440,2)) -> 12 | F2: =SUMIF(KitchenRuns!$B$2:$B$37,A2,KitchenRuns!$I$2:$I$37) -> 10 | G2: =F2/60*Guide!$B$4 -> 4 | H2: =SUMIFS(Payments!$E$2:$E$37,Payments!$B$2:$B$37,A2,Payments!$D$2:$D$37,"REFUND_GOODWILL") -> 3 | I2: =G2+H2 -> 7 | J2: =ABS(SUMIFS(Payments!$E$2:$E$37,Payments!$B$2:$B$37,A2,Payments!$D$2:$D$37,"CAPTURE")-SUMIF(OrderLines!$B$2:$B$37,A2,OrderLines!$I$2:$I$37)) -> 0
A3: =Orders!A3 -> O002 | B3: =COUNTIFS(KitchenRuns!$B$2:$B$37,A3,KitchenRuns!$E$2:$E$37,"BLOCKED") -> 1 | C3: =Orders!D3 -> 46283.469 | D3: =SUMIFS(KitchenRuns!$K$2:$K$37,KitchenRuns!$B$2:$B$37,A3,KitchenRuns!$E$2:$E$37,"SUCCESS") -> 46283.48 | E3: =MAX(0,ROUND((D3-C3)*1440,2)) -> 15 | F3: =SUMIF(KitchenRuns!$B$2:$B$37,A3,KitchenRuns!$I$2:$I$37) -> 10 | G3: =F3/60*Guide!$B$4 -> 4 | H3: =SUMIFS(Payments!$E$2:$E$37,Payments!$B$2:$B$37,A3,Payments!$D$2:$D$37,"REFUND_GOODWILL") -> 3 | I3: =G3+H3 -> 7 | J3: =ABS(SUMIFS(Payments!$E$2:$E$37,Payments!$B$2:$B$37,A3,Payments!$D$2:$D$37,"CAPTURE")-SUMIF(OrderLines!$B$2:$B$37,A3,OrderLines!$I$2:$I$37)) -> 0
A4: =Orders!A4 -> O003 | B4: =COUNTIFS(KitchenRuns!$B$2:$B$37,A4,KitchenRuns!$E$2:$E$37,"BLOCKED") -> 1 | C4: =Orders!D4 -> 46283.47 | D4: =SUMIFS(KitchenRuns!$K$2:$K$37,KitchenRuns!$B$2:$B$37,A4,KitchenRuns!$E$2:$E$37,"SUCCESS") -> 46283.482 | E4: =MAX(0,ROUND((D4-C4)*1440,2)) -> 17 | F4: =SUMIF(KitchenRuns!$B$2:$B$37,A4,KitchenRuns!$I$2:$I$37) -> 10 | G4: =F4/60*Guide!$B$4 -> 4 | H4: =SUMIFS(Payments!$E$2:$E$37,Payments!$B$2:$B$37,A4,Payments!$D$2:$D$37,"REFUND_GOODWILL") -> 3 | I4: =G4+H4 -> 7 | J4: =ABS(SUMIFS(Payments!$E$2:$E$37,Payments!$B$2:$B$37,A4,Payments!$D$2:$D$37,"CAPTURE")-SUMIF(OrderLines!$B$2:$B$37,A4,OrderLines!$I$2:$I$37)) -> 0
A5: =Orders!A5 -> O004 | B5: =COUNTIFS(KitchenRuns!$B$2:$B$37,A5,KitchenRuns!$E$2:$E$37,"BLOCKED") -> 1 | C5: =Orders!D5 -> 46283.471 | D5: =SUMIFS(KitchenRuns!$K$2:$K$37,KitchenRuns!$B$2:$B$37,A5,KitchenRuns!$E$2:$E$37,"SUCCESS") -> 46283.485 | E5: =MAX(0,ROUND((D5-C5)*1440,2)) -> 20 | F5: =SUMIF(KitchenRuns!$B$2:$B$37,A5,KitchenRuns!$I$2:$I$37) -> 10 | G5: =F5/60*Guide!$B$4 -> 4 | H5: =SUMIFS(Payments!$E$2:$E$37,Payments!$B$2:$B$37,A5,Payments!$D$2:$D$37,"REFUND_GOODWILL") -> 3 | I5: =G5+H5 -> 7 | J5: =ABS(SUMIFS(Payments!$E$2:$E$37,Payments!$B$2:$B$37,A5,Payments!$D$2:$D$37,"CAPTURE")-SUMIF(OrderLines!$B$2:$B$37,A5,OrderLines!$I$2:$I$37)) -> 0
A6: =Orders!A6 -> O005 | B6: =COUNTIFS(KitchenRuns!$B$2:$B$37,A6,KitchenRuns!$E$2:$E$37,"BLOCKED") -> 1 | C6: =Orders!D6 -> 46283.472 | D6: =SUMIFS(KitchenRuns!$K$2:$K$37,KitchenRuns!$B$2:$B$37,A6,KitchenRuns!$E$2:$E$37,"SUCCESS") -> 46283.487 | E6: =MAX(0,ROUND((D6-C6)*1440,2)) -> 22 | F6: =SUMIF(KitchenRuns!$B$2:$B$37,A6,KitchenRuns!$I$2:$I$37) -> 10 | G6: =F6/60*Guide!$B$4 -> 4 | H6: =SUMIFS(Payments!$E$2:$E$37,Payments!$B$2:$B$37,A6,Payments!$D$2:$D$37,"REFUND_GOODWILL") -> 4 | I6: =G6+H6 -> 8 | J6: =ABS(SUMIFS(Payments!$E$2:$E$37,Payments!$B$2:$B$37,A6,Payments!$D$2:$D$37,"CAPTURE")-SUMIF(OrderLines!$B$2:$B$37,A6,OrderLines!$I$2:$I$37)) -> 0
A7: =Orders!A7 -> O006 | B7: =COUNTIFS(KitchenRuns!$B$2:$B$37,A7,KitchenRuns!$E$2:$E$37,"BLOCKED") -> 1 | C7: =Orders!D7 -> 46283.472 | D7: =SUMIFS(KitchenRuns!$K$2:$K$37,KitchenRuns!$B$2:$B$37,A7,KitchenRuns!$E$2:$E$37,"SUCCESS") -> 46283.49 | E7: =MAX(0,ROUND((D7-C7)*1440,2)) -> 26 | F7: =SUMIF(KitchenRuns!$B$2:$B$37,A7,KitchenRuns!$I$2:$I$37) -> 10 | G7: =F7/60*Guide!$B$4 -> 4 | H7: =SUMIFS(Payments!$E$2:$E$37,Payments!$B$2:$B$37,A7,Payments!$D$2:$D$37,"REFUND_GOODWILL") -> 4 | I7: =G7+H7 -> 8 | J7: =ABS(SUMIFS(Payments!$E$2:$E$37,Payments!$B$2:$B$37,A7,Payments!$D$2:$D$37,"CAPTURE")-SUMIF(OrderLines!$B$2:$B$37,A7,OrderLines!$I$2:$I$37)) -> 0
A8: =Orders!A8 -> O007 | B8: =COUNTIFS(KitchenRuns!$B$2:$B$37,A8,KitchenRuns!$E$2:$E$37,"BLOCKED") -> 0 | C8: =Orders!D8 -> 46283.473 | D8: =SUMIFS(KitchenRuns!$K$2:$K$37,KitchenRuns!$B$2:$B$37,A8,KitchenRuns!$E$2:$E$37,"SUCCESS") -> 46283.468 | E8: =MAX(0,ROUND((D8-C8)*1440,2)) -> 0 | F8: =SUMIF(KitchenRuns!$B$2:$B$37,A8,KitchenRuns!$I$2:$I$37) -> 0 | G8: =F8/60*Guide!$B$4 -> 0 | H8: =SUMIFS(Payments!$E$2:$E$37,Payments!$B$2:$B$37,A8,Payments!$D$2:$D$37,"REFUND_GOODWILL") -> 0 | I8: =G8+H8 -> 0 | J8: =ABS(SUMIFS(Payments!$E$2:$E$37,Payments!$B$2:$B$37,A8,Payments!$D$2:$D$37,"CAPTURE")-SUMIF(OrderLines!$B$2:$B$37,A8,OrderLines!$I$2:$I$37)) -> 0
A9: =Orders!A9 -> O008 | B9: =COUNTIFS(KitchenRuns!$B$2:$B$37,A9,KitchenRuns!$E$2:$E$37,"BLOCKED") -> 0 | C9: =Orders!D9 -> 46283.474 | D9: =SUMIFS(KitchenRuns!$K$2:$K$37,KitchenRuns!$B$2:$B$37,A9,KitchenRuns!$E$2:$E$37,"SUCCESS") -> 46283.469 | E9: =MAX(0,ROUND((D9-C9)*1440,2)) -> 0 | F9: =SUMIF(KitchenRuns!$B$2:$B$37,A9,KitchenRuns!$I$2:$I$37) -> 0 | G9: =F9/60*Guide!$B$4 -> 0 | H9: =SUMIFS(Payments!$E$2:$E$37,Payments!$B$2:$B$37,A9,Payments!$D$2:$D$37,"REFUND_GOODWILL") -> 0 | I9: =G9+H9 -> 0 | J9: =ABS(SUMIFS(Payments!$E$2:$E$37,Payments!$B$2:$B$37,A9,Payments!$D$2:$D$37,"CAPTURE")-SUMIF(OrderLines!$B$2:$B$37,A9,OrderLines!$I$2:$I$37)) -> 0
A10: =Orders!A10 -> O009 | B10: =COUNTIFS(KitchenRuns!$B$2:$B$37,A10,KitchenRuns!$E$2:$E$37,"BLOCKED") -> 0 | C10: =Orders!D10 -> 46283.474 | D10: =SUMIFS(KitchenRuns!$K$2:$K$37,KitchenRuns!$B$2:$B$37,A10,KitchenRuns!$E$2:$E$37,"SUCCESS") -> 46283.47 | E10: =MAX(0,ROUND((D10-C10)*1440,2)) -> 0 | F10: =SUMIF(KitchenRuns!$B$2:$B$37,A10,KitchenRuns!$I$2:$I$37) -> 0 | G10: =F10/60*Guide!$B$4 -> 0 | H10: =SUMIFS(Payments!$E$2:$E$37,Payments!$B$2:$B$37,A10,Payments!$D$2:$D$37,"REFUND_GOODWILL") -> 0 | I10: =G10+H10 -> 0 | J10: =ABS(SUMIFS(Payments!$E$2:$E$37,Payments!$B$2:$B$37,A10,Payments!$D$2:$D$37,"CAPTURE")-SUMIF(OrderLines!$B$2:$B$37,A10,OrderLines!$I$2:$I$37)) -> 0
A11: =Orders!A11 -> O010 | B11: =COUNTIFS(KitchenRuns!$B$2:$B$37,A11,KitchenRuns!$E$2:$E$37,"BLOCKED") -> 0 | C11: =Orders!D11 -> 46283.475 | D11: =SUMIFS(KitchenRuns!$K$2:$K$37,KitchenRuns!$B$2:$B$37,A11,KitchenRuns!$E$2:$E$37,"SUCCESS") -> 46283.47 | E11: =MAX(0,ROUND((D11-C11)*1440,2)) -> 0 | F11: =SUMIF(KitchenRuns!$B$2:$B$37,A11,KitchenRuns!$I$2:$I$37) -> 0 | G11: =F11/60*Guide!$B$4 -> 0 | H11: =SUMIFS(Payments!$E$2:$E$37,Payments!$B$2:$B$37,A11,Payments!$D$2:$D$37,"REFUND_GOODWILL") -> 0 | I11: =G11+H11 -> 0 | J11: =ABS(SUMIFS(Payments!$E$2:$E$37,Payments!$B$2:$B$37,A11,Payments!$D$2:$D$37,"CAPTURE")-SUMIF(OrderLines!$B$2:$B$37,A11,OrderLines!$I$2:$I$37)) -> 0
A12: =Orders!A12 -> O011 | B12: =COUNTIFS(KitchenRuns!$B$2:$B$37,A12,KitchenRuns!$E$2:$E$37,"BLOCKED") -> 0 | C12: =Orders!D12 -> 46283.476 | D12: =SUMIFS(KitchenRuns!$K$2:$K$37,KitchenRuns!$B$2:$B$37,A12,KitchenRuns!$E$2:$E$37,"SUCCESS") -> 46283.471 | E12: =MAX(0,ROUND((D12-C12)*1440,2)) -> 0 | F12: =SUMIF(KitchenRuns!$B$2:$B$37,A12,KitchenRuns!$I$2:$I$37) -> 0 | G12: =F12/60*Guide!$B$4 -> 0 | H12: =SUMIFS(Payments!$E$2:$E$37,Payments!$B$2:$B$37,A12,Payments!$D$2:$D$37,"REFUND_GOODWILL") -> 0 | I12: =G12+H12 -> 0 | J12: =ABS(SUMIFS(Payments!$E$2:$E$37,Payments!$B$2:$B$37,A12,Payments!$D$2:$D$37,"CAPTURE")-SUMIF(OrderLines!$B$2:$B$37,A12,OrderLines!$I$2:$I$37)) -> 0
A13: =Orders!A13 -> O012 | B13: =COUNTIFS(KitchenRuns!$B$2:$B$37,A13,KitchenRuns!$E$2:$E$37,"BLOCKED") -> 0 | C13: =Orders!D13 -> 46283.476 | D13: =SUMIFS(KitchenRuns!$K$2:$K$37,KitchenRuns!$B$2:$B$37,A13,KitchenRuns!$E$2:$E$37,"SUCCESS") -> 46283.472 | E13: =MAX(0,ROUND((D13-C13)*1440,2)) -> 0 | F13: =SUMIF(KitchenRuns!$B$2:$B$37,A13,KitchenRuns!$I$2:$I$37) -> 0 | G13: =F13/60*Guide!$B$4 -> 0 | H13: =SUMIFS(Payments!$E$2:$E$37,Payments!$B$2:$B$37,A13,Payments!$D$2:$D$37,"REFUND_GOODWILL") -> 0 | I13: =G13+H13 -> 0 | J13: =ABS(SUMIFS(Payments!$E$2:$E$37,Payments!$B$2:$B$37,A13,Payments!$D$2:$D$37,"CAPTURE")-SUMIF(OrderLines!$B$2:$B$37,A13,OrderLines!$I$2:$I$37)) -> 0
... A31: =Orders!A31 -> O030 | B31: =COUNTIFS(KitchenRuns!$B$2:$B$37,A31,KitchenRuns!$E$2:$E$37,"BLOCKED") -> 0 | C31: =Orders!D31 -> 46283.489 | D31: =SUMIFS(KitchenRuns!$K$2:$K$37,KitchenRuns!$B$2:$B$37,A31,KitchenRuns!$E$2:$E$37,"SUCCESS") -> 46283.484 | E31: =MAX(0,ROUND((D31-C31)*1440,2)) -> 0 | F31: =SUMIF(KitchenRuns!$B$2:$B$37,A31,KitchenRuns!$I$2:$I$37) -> 0 | G31: =F31/60*Guide!$B$4 -> 0 | H31: =SUMIFS(Payments!$E$2:$E$37,Payments!$B$2:$B$37,A31,Payments!$D$2:$D$37,"REFUND_GOODWILL") -> 0 | I31: =G31+H31 -> 0 | J31: =ABS(SUMIFS(Payments!$E$2:$E$37,Payments!$B$2:$B$37,A31,Payments!$D$2:$D$37,"CAPTURE")-SUMIF(OrderLines!$B$2:$B$37,A31,OrderLines!$I$2:$I$37)) -> 0

Sheet Guide
A1: Topic | B1: Definition
A2: Generation | B2: Seven source tables generated in Gemini 3.6 Flash on 24 September 2026; prompts and correction retained in supporting provenance. Codex packaged and validated the workbook.
A3: Gemini source | B3: https://gemini.google.com/app/ac38f352f91d6520
A4: Labor rate USD/hour | B4: 24
A5: Synthetic scope | B5: 30 fictional orders on 18 September 2026. Menu labels and prices are illustrative, not a verified current Sweetgreen menu. All timestamps are UTC.
A6: Curveball | B6: Nightly cached availability disagrees with current kitchen state; hypothetical cadence, not an observed Sweetgreen process.
A7: Row grain | B7: Customers: customer; MenuItems: menu item; Availability: item with cached/current states; Orders: order; OrderLines: item line; KitchenRuns: attempt; Payments: event.
A8: Keys | B8: customer_id links Orders to Customers; order_id joins lines/runs/payments; item_id and final_item_id join MenuItems; Availability joins by item_id.
A9: Metric definition | B9: Readiness lateness = max(0, successful ready_at minus promised_at), in minutes. Affected orders have a BLOCKED run. Labor sums extra_labor_min over all attempts.
A10: Timing simplification | B10: The six recovery orders are collected immediately on readiness. Other orders have separate readiness and collection times. Availability is checked before prep.
A11: Costs | B11: Labor is capacity consumed, not necessarily incremental payroll. Refunds are goodwill cash adjustments. Food waste is excluded. $44 is exposure, not guaranteed savings.
A12: Status interpretation | B12: Orders.status is the final COMPLETED state. accepted_at evidences CP1; no independent acceptance event log is claimed. BLOCKED and SUCCESS attempts are separate KitchenRuns rows.
A13: Consent | B13: Changed lines preserve original and final item IDs plus consent and change_agreed_at. Blank consent on unchanged lines means no change consent required.
A14: Control coverage | B14: CP5 cancellations and authorization voids are unseeded. No quality-remake examples are seeded. Proposed owner IDs, specification versions, original payment references and provider response IDs are detailed in the map register.
A15: Judgment notes | B15: Three recovery notes express urgency, estimated prep time, queue impact and consent. They are scenario inputs, not proof of causal attribution or allergy safety.
A16: Gemini review | B16: Gemini corrected six ready_at values and retracted unsupported food-waste/savings claims. Original generated source cells otherwise retained; derived columns and formula summaries added locally.
... A20: Lab 2 scope | B20: D2: current item availability plus freshness routing. Ingredient-level customizations and stock reservations require a richer production schema; this sandbox is item-level.
